redisbeater/__init__.py
redisbeater/decoder.py
redisbeater/schedulers.py
redisbeater/schedules.py
redisbeater/utils.py
celery_redisbeater-1.0.1.dist-info/LICENSE
celery_redisbeater-1.0.1.dist-info/METADATA
celery_redisbeater-1.0.1.dist-info/WHEEL
celery_redisbeater-1.0.1.dist-info/top_level.txt
celery_redisbeater-1.0.1.dist-info/RECORD
