Metadata-Version: 2.1
Name: celery-redisbeater
Version: 1.0.1
Summary: A Celery Beat Scheduler using Redis for persistent storage
Home-page: https://github.com/saber-solooki/redisbeater
Author: Saber Solooki
Author-email: saber.solooki@gmail.com
License: Apache License, Version 2.0
Keywords: python,celery,beat,redis
Platform: UNKNOWN
Classifier: Development Status :: 5 - Production/Stable
Classifier: License :: OSI Approved :: Apache Software License
Classifier: Topic :: System :: Distributed Computing
Classifier: Topic :: Software Development :: Object Brokering
Classifier: Programming Language :: Python
Classifier: Programming Language :: Python :: 3
Classifier: Programming Language :: Python :: 3.6
Classifier: Programming Language :: Python :: 3.7
Classifier: Programming Language :: Python :: 3.8
Classifier: Programming Language :: Python :: 3.9
Classifier: Programming Language :: Python :: Implementation :: CPython
Classifier: Operating System :: OS Independent
License-File: LICENSE
Requires-Dist: redis (>=3.2)
Requires-Dist: celery (>=4.2)
Requires-Dist: python-dateutil
Requires-Dist: tenacity
